indicpy4health/__init__.py
indicpy4health/ruleEngine.py
indicpy4health-0.1.2.dist-info/LICENSE
indicpy4health-0.1.2.dist-info/METADATA
indicpy4health-0.1.2.dist-info/WHEEL
indicpy4health-0.1.2.dist-info/RECORD
