Metadata-Version: 2.1
Name: indicpy4health
Version: 0.1.2
Summary: IndicPy4Health is a Lightweight, Fast, and Intuitive Indicator Calculations Python Library from Health data.
Author: Javier González-Galindo
Author-email: jgonzalezga.iacs@aragon.es
Requires-Python: >=3.9
Classifier: Programming Language :: Python :: 3
Classifier: Programming Language :: Python :: 3.9
Classifier: Programming Language :: Python :: 3.10
Classifier: Programming Language :: Python :: 3.11
Requires-Dist: duckdb (>=1.2.2,<2.0.0)
Requires-Dist: pandas (>=2.2.3,<3.0.0)
